quillion/__init__.py
quillion/components/__init__.py
quillion/components/base.py
quillion/components/state/__init__.py
quillion/components/state/base.py
quillion/components/ui/__init__.py
quillion/components/ui/base/anchor.py
quillion/components/ui/base/article.py
quillion/components/ui/base/aside.py
quillion/components/ui/base/bold.py
quillion/components/ui/base/break_line.py
quillion/components/ui/base/button.py
quillion/components/ui/base/container.py
quillion/components/ui/base/dialog.py
quillion/components/ui/base/element.py
quillion/components/ui/base/emphasis.py
quillion/components/ui/base/footer.py
quillion/components/ui/base/form.py
quillion/components/ui/base/heading.py
quillion/components/ui/base/horizontal_rule.py
quillion/components/ui/base/italic.py
quillion/components/ui/base/label.py
quillion/components/ui/base/legend.py
quillion/components/ui/base/link.py
quillion/components/ui/base/list_item.py
quillion/components/ui/base/main.py
quillion/components/ui/base/mark.py
quillion/components/ui/base/menu.py
quillion/components/ui/base/navigation.py
quillion/components/ui/base/option.py
quillion/components/ui/base/ordered_list.py
quillion/components/ui/base/paragraph.py
quillion/components/ui/base/preformatted.py
quillion/components/ui/base/prompt.py
quillion/components/ui/base/scipt.py
quillion/components/ui/base/section.py
quillion/components/ui/base/select.py
quillion/components/ui/base/small.py
quillion/components/ui/base/span.py
quillion/components/ui/base/strikethrough.py
quillion/components/ui/base/strong.py
quillion/components/ui/base/style.py
quillion/components/ui/base/summary.py
quillion/components/ui/base/table.py
quillion/components/ui/base/table_cell.py
quillion/components/ui/base/table_header.py
quillion/components/ui/base/table_row.py
quillion/components/ui/base/template.py
quillion/components/ui/base/text.py
quillion/components/ui/base/textarea.py
quillion/components/ui/base/underline.py
quillion/components/ui/base/unordered_list.py
quillion-0.2.10.dist-info/METADATA
quillion-0.2.10.dist-info/WHEEL
quillion-0.2.10.dist-info/entry_points.txt
quillion-0.2.10.dist-info/licenses/LICENSE
quillion-0.2.10.dist-info/RECORD
