Metadata-Version: 2.4
Name: quillion
Version: 0.2.10
Summary: Modern asynchronous web framework
License: MIT
License-File: LICENSE
Keywords: web,framework,async
Author: anybody
Requires-Python: >=3.9,<4.0
Classifier: Development Status :: 3 - Alpha
Classifier: Intended Audience :: Developers
Classifier: License :: OSI Approved :: MIT License
Classifier: Programming Language :: Python :: 3
Classifier: Programming Language :: Python :: 3.9
Classifier: Programming Language :: Python :: 3.10
Classifier: Programming Language :: Python :: 3.11
Classifier: Programming Language :: Python :: 3.12
Classifier: Programming Language :: Python :: 3.13
Classifier: Programming Language :: Python :: 3.14
Classifier: Topic :: Communications :: Chat
Classifier: Topic :: Software Development :: Libraries :: Application Frameworks
Classifier: Typing :: Typed
Provides-Extra: uvloop
Requires-Dist: aiohttp (==3.12.15)
Requires-Dist: cryptography (>=42.0,<43.0)
Requires-Dist: nest-asyncio (>=1.6.0,<2.0.0)
Requires-Dist: pydantic (>=2.0,<3.0)
Requires-Dist: quillion-cli (>=0.1.3,<0.2.0)
Requires-Dist: websockets (>=12.0,<13.0)
Project-URL: Homepage, https://github.com/base-of-base/quillion
Project-URL: Repository, https://github.com/base-of-base/quillion
